{"@module": "pymatgen.core.structure", "@class": "Structure", "charge": null, "lattice": {"matrix": [[22.760981, -1.549121, 0.0], [22.760981, 1.549121, 0.0], [22.655547, 0.0, 2.681084]], "a": 22.81363697342013, "b": 22.81363697342013, "c": 22.813636739552617, "alpha": 7.78713598253484, "beta": 7.78713598253484, "gamma": 7.78713589158054, "volume": 189.06743577726556}, "sites": [{"species": [{"element": "Si", "occu": 1}], "abc": [0.888936, 0.888936, 0.888936], "xyz": [60.605442140423996, 0.0, 2.3833120866239996], "label": "Si", "properties": {"magmom": -0.0}}, {"species": [{"element": "Si", "occu": 1}], "abc": [0.518517, 0.518517, 0.518517], "xyz": [35.351197434153, 0.0, 1.3901876324279998], "label": "Si", "properties": {"magmom": -0.0}}, {"species": [{"element": "Si", "occu": 1}], "abc": [0.148104, 0.148104, 0.148104], "xyz": [10.097361792936, 0.0, 0.397079264736], "label": "Si", "properties": {"magmom": -0.0}}, {"species": [{"element": "Si", "occu": 1}], "abc": [0.296201, 0.296201, 0.296201], "xyz": [20.194246343309, 0.0, 0.7941397618839999], "label": "Si", "properties": {"magmom": 0.0}}, {"species": [{"element": "Si", "occu": 1}], "abc": [0.592602, 0.592602, 0.592602], "xyz": [40.402128188418, 0.0, 1.5888157405679997], "label": "Si", "properties": {"magmom": 0.0}}, {"species": [{"element": "Si", "occu": 1}], "abc": [0.999906, 0.999906, 0.999906], "xyz": [68.17110031415399, 0.0, 2.6808319781039995], "label": "Si", "properties": {"magmom": 0.0}}, {"species": [{"element": "Si", "occu": 1}], "abc": [0.444377, 0.444377, 0.444377], "xyz": [30.296516916893, 0.0, 1.191412064668], "label": "Si", "properties": {"magmom": -0.0}}, {"species": [{"element": "Si", "occu": 1}], "abc": [0.370293, 0.370293, 0.370293], "xyz": [25.245654340137, 0.0, 0.9927866376119999], "label": "Si", "properties": {"magmom": 0.0}}, {"species": [{"element": "Si", "occu": 1}], "abc": [0.740689, 0.740689, 0.740689], "xyz": [50.498330963701, 0.0, 1.9858494268759999], "label": "Si", "properties": {"magmom": 0.0}}, {"species": [{"element": "C", "occu": 1}], "abc": [0.398133, 0.398133, 0.398133], "xyz": [27.143716190697003, 0.0, 1.067428016172], "label": "C", "properties": {"magmom": -0.0}}, {"species": [{"element": "C", "occu": 1}], "abc": [0.768599, 0.768599, 0.768599], "xyz": [52.401165239891, 0.0, 2.0606784813159997], "label": "C", "properties": {"magmom": 0.0}}, {"species": [{"element": "C", "occu": 1}], "abc": [0.32401, 0.32401, 0.32401], "xyz": [22.09019469109, 0.0, 0.86869802684], "label": "C", "properties": {"magmom": -0.0}}, {"species": [{"element": "C", "occu": 1}], "abc": [0.027829, 0.027829, 0.027829], "xyz": [1.897311897961, 0.0, 0.07461188663599999], "label": "C", "properties": {"magmom": -0.0}}, {"species": [{"element": "C", "occu": 1}], "abc": [0.472195, 0.472195, 0.472195], "xyz": [32.193078862255, 0.0, 1.2659944593799999], "label": "C", "properties": {"magmom": 0.0}}, {"species": [{"element": "C", "occu": 1}], "abc": [0.916823, 0.916823, 0.916823], "xyz": [62.50670833390701, 0.0, 2.458079476132], "label": "C", "properties": {"magmom": 0.0}}, {"species": [{"element": "C", "occu": 1}], "abc": [0.176036, 0.176036, 0.176036], "xyz": [12.001695974323999, 0.0, 0.471967303024], "label": "C", "properties": {"magmom": 0.0}}, {"species": [{"element": "C", "occu": 1}], "abc": [0.546356, 0.546356, 0.546356], "xyz": [37.249191107204, 0.0, 1.4648263299039999], "label": "C", "properties": {"magmom": 0.0}}, {"species": [{"element": "C", "occu": 1}], "abc": [0.620392, 0.620392, 0.620392], "xyz": [42.296781163528, 0.0, 1.663323064928], "label": "C", "properties": {"magmom": -0.0}}], "@version": null}